mind_palace/__init__.py
mind_palace/__main__.py
mind_palace-0.1.0.dist-info/entry_points.txt
mind_palace-0.1.0.dist-info/WHEEL
mind_palace-0.1.0.dist-info/METADATA
mind_palace-0.1.0.dist-info/RECORD
